sbom_compliance_tool/__init__.py
sbom_compliance_tool/__main__.py
sbom_compliance_tool/compatibility.py
sbom_compliance_tool/compliance_tool.py
sbom_compliance_tool/config.py
sbom_compliance_tool/format.py
sbom_compliance_tool-0.0.9.dist-info/GPL-3.0-or-later.txt
sbom_compliance_tool-0.0.9.dist-info/METADATA
sbom_compliance_tool-0.0.9.dist-info/WHEEL
sbom_compliance_tool-0.0.9.dist-info/entry_points.txt
sbom_compliance_tool-0.0.9.dist-info/top_level.txt
sbom_compliance_tool-0.0.9.dist-info/RECORD
